{
    "white": true,
    "grid": [
        {
            "class": "Rook",
            "unicode": "&#x2656;",
            "white": true,
            "x": 0,
            "y": 7
        },
        {
            "class": "Knight",
            "unicode": "&#x265E;",
            "white": false,
            "x": 1,
            "y": 7
        },
        {
            "class": "King",
            "unicode": "&#x2654;",
            "white": true,
            "x": 3,
            "y": 0,
            "check": false
        },
        {
            "class": "King",
            "unicode": "&#x265A;",
            "white": false,
            "x": 2,
            "y": 7,
            "check": true
        }
    ]
}